lovelyplots/__init__.py
lovelyplots/utils.py
lovelyplots/styles/ipynb.mplstyle
lovelyplots/styles/cmaps/cmap-cividis.mplstyle
lovelyplots/styles/cmaps/cmap-inferno.mplstyle
lovelyplots/styles/cmaps/cmap-magma.mplstyle
lovelyplots/styles/cmaps/cmap-plasma.mplstyle
lovelyplots/styles/cmaps/cmap-viridis.mplstyle
lovelyplots/styles/colors/colors10.mplstyle
lovelyplots/styles/colors/colors5-light.mplstyle
lovelyplots/styles/colors/colors5.mplstyle
lovelyplots/styles/colors/colorsblind10.mplstyle
lovelyplots/styles/colors/colorsblind34.mplstyle
lovelyplots/styles/combination/colors10-ls.mplstyle
lovelyplots/styles/combination/colors10-markers.mplstyle
lovelyplots/styles/journals/nature.mplstyle
lovelyplots/styles/journals/paper.mplstyle
lovelyplots/styles/linestyles/ls5.mplstyle
lovelyplots/styles/markerstyle/marker7.mplstyle
lovelyplots/styles/utils/svg_no_fonttype.mplstyle
lovelyplots/styles/utils/use_mathtext.mplstyle
lovelyplots/styles/utils/use_tex.mplstyle
lovelyplots-1.0.2.dist-info/LICENCE
lovelyplots-1.0.2.dist-info/METADATA
lovelyplots-1.0.2.dist-info/WHEEL
lovelyplots-1.0.2.dist-info/top_level.txt
lovelyplots-1.0.2.dist-info/RECORD
