Metadata-Version: 2.1
Name: lovelyplots
Version: 1.0.2
Summary: Format Matplotlib Plots for thesis, scientific papers and reports.
Home-page: https://github.com/killiansheriff/LovelyPlots
Author: Killian Sheriff
Author-email: killian.sheriff@gmail.com
License: MIT
Keywords: matplotlib-style-sheets,matplotlib-figures,scientific-papers,PhD,thesis-template,matplotlib-styles,Adobe Illustrator,Latex,latex-figures
Classifier: Framework :: Matplotlib
Classifier: License :: OSI Approved :: MIT License
Classifier: Programming Language :: Python :: 3
License-File: LICENCE
Requires-Dist: matplotlib
